{
  "date": "2025-12-02",
  "symbols": [
    {
      "symbol": "SPY",
      "commit": "42d04e6e8e3161c13df5787f730bdd11324fe33cb1b9d436eb0435b65fd7dd05",
      "commit_bar_ts_et": "2025-12-02T15:55:00-05:00",
      "committed_at_utc": "2025-12-02T20:58:02.097934+00:00",
      "commit_inputs": {
        "symbol": "SPY",
        "prediction": 0,
        "commit_bar_ts_et": "2025-12-02T15:55:00-05:00",
        "timestamp_commit_utc": "2025-12-02T20:58:02.097934+00:00",
        "context": "2025-12-02|SPY|NYSE|close",
        "p_commit": 681.57
      },
      "prediction": 0,
      "salt": "3a5d296dda23d499f6b2ae889290fadd",
      "outcome": 1,
      "symbol_bits": "01",
      "close_prev": 678.739990234375,
      "close_today": 679.3275146484375,
      "provider": "yfinance",
      "tie": false,
      "context": "2025-12-02|SPY|NYSE|close",
      "p_commit": 681.57,
      "p_reveal": 679.3275146484375,
      "delta": -2.24248535156255,
      "sign_bit": 0,
      "mag_q": 224,
      "symbol_bytes_hex": "000100e0",
      "revealed_at_utc": "2025-12-02T21:30:14.248368+00:00"
    },
    {
      "symbol": "AAPL",
      "commit": "f402375a68eb65bbffc01286b640f3f0563cbfd053ec3b3a4ffe5ebfb1446935",
      "commit_bar_ts_et": "2025-12-02T15:55:00-05:00",
      "committed_at_utc": "2025-12-02T20:58:02.876318+00:00",
      "commit_inputs": {
        "symbol": "AAPL",
        "prediction": 1,
        "commit_bar_ts_et": "2025-12-02T15:55:00-05:00",
        "timestamp_commit_utc": "2025-12-02T20:58:02.876318+00:00",
        "context": "2025-12-02|AAPL|NASDAQ|close",
        "p_commit": 285.8
      },
      "prediction": 1,
      "salt": "ebbbc78cfc667ebf58c3c0f67acd6af8",
      "outcome": 1,
      "symbol_bits": "11",
      "close_prev": 276.1400146484375,
      "close_today": 282.6300964355469,
      "provider": "yfinance",
      "tie": false,
      "context": "2025-12-02|AAPL|NASDAQ|close",
      "p_commit": 285.8,
      "p_reveal": 282.6300964355469,
      "delta": -3.1699035644531364,
      "sign_bit": 0,
      "mag_q": 255,
      "symbol_bytes_hex": "010100ff",
      "revealed_at_utc": "2025-12-02T21:30:15.117719+00:00"
    }
  ],
  "meta": {
    "generated_at_utc": "2025-12-02T20:58:00.883807+00:00",
    "code_commit": "45322ed9a4f935b7aa185f6906af16f77796a877"
  }
}