{
  "date": "2026-01-29",
  "symbols": [
    {
      "symbol": "SPY",
      "commit": "6f15f2b998e6476658844ace2b77ee6009ed4c6f77440b0707cbf271f969b172",
      "commit_bar_ts_et": "2026-01-29T15:55:00-05:00",
      "committed_at_utc": "2026-01-29T21:03:49.305380+00:00",
      "commit_inputs": {
        "symbol": "SPY",
        "prediction": 1,
        "p_commit": 693.58,
        "commit_bar_ts_et": "2026-01-29T15:55:00-05:00",
        "timestamp_commit_utc": "2026-01-29T21:03:49.305380+00:00",
        "context": "2026-01-29|SPY|NYSE|close"
      }
    },
    {
      "symbol": "AAPL",
      "commit": "448bde7ed36c8f4262f255a94bcfab3bdfcbb1da6295abb162c1f8f80807b4c0",
      "commit_bar_ts_et": "2026-01-29T15:55:00-05:00",
      "committed_at_utc": "2026-01-29T21:03:50.099966+00:00",
      "commit_inputs": {
        "symbol": "AAPL",
        "prediction": 0,
        "p_commit": 258.18,
        "commit_bar_ts_et": "2026-01-29T15:55:00-05:00",
        "timestamp_commit_utc": "2026-01-29T21:03:50.099966+00:00",
        "context": "2026-01-29|AAPL|NASDAQ|close"
      }
    }
  ],
  "meta": {
    "generated_at_utc": "2026-01-29T21:03:48.132035+00:00",
    "code_commit": "a930bbe03d200d353079ca3d043ce29cb92c9a50"
  }
}