{
  "date": "2026-05-29",
  "symbols": [
    {
      "symbol": "SPY",
      "commit": "35db39613f5587b9324f4cc3c2aa7ad72d9cccab8ecf31fa3539dce6edc3c6d0",
      "commit_bar_ts_et": "2026-05-29T15:55:00-04:00",
      "committed_at_utc": "2026-05-29T22:21:36.645767+00:00",
      "commit_inputs": {
        "symbol": "SPY",
        "prediction": 1,
        "commit_bar_ts_et": "2026-05-29T15:55:00-04:00",
        "timestamp_commit_utc": "2026-05-29T22:21:36.645767+00:00",
        "context": "2026-05-29|SPY|NYSE|close",
        "p_commit": 756.45
      },
      "prediction": 1,
      "salt": "7c17bd33cf3effc991c2af4419d4c0e9",
      "outcome": 1,
      "symbol_bits": "11",
      "close_prev": 749.22998046875,
      "close_today": 754.6900024414062,
      "provider": "yfinance",
      "tie": false,
      "context": "2026-05-29|SPY|NYSE|close",
      "p_commit": 756.45,
      "p_reveal": 754.6900024414062,
      "delta": -1.7599975585937955,
      "sign_bit": 0,
      "mag_q": 175,
      "symbol_bytes_hex": "010100af",
      "revealed_at_utc": "2026-05-29T22:41:52.071650+00:00"
    },
    {
      "symbol": "AAPL",
      "commit": "17ca26016ded2ff6040d161f43e4fc30befd7bd9e56b3b9fb51792da0c3c03dc",
      "commit_bar_ts_et": "2026-05-29T15:55:00-04:00",
      "committed_at_utc": "2026-05-29T22:21:37.363741+00:00",
      "commit_inputs": {
        "symbol": "AAPL",
        "prediction": 1,
        "commit_bar_ts_et": "2026-05-29T15:55:00-04:00",
        "timestamp_commit_utc": "2026-05-29T22:21:37.363741+00:00",
        "context": "2026-05-29|AAPL|NASDAQ|close",
        "p_commit": 312.06
      },
      "prediction": 1,
      "salt": "9f9712c3b35948467c1102a294758a9b",
      "outcome": 0,
      "symbol_bits": "10",
      "close_prev": 309.57000732421875,
      "close_today": 309.5299987792969,
      "provider": "yfinance",
      "tie": false,
      "context": "2026-05-29|AAPL|NASDAQ|close",
      "p_commit": 312.06,
      "p_reveal": 309.5299987792969,
      "delta": -2.5300012207031273,
      "sign_bit": 0,
      "mag_q": 253,
      "symbol_bytes_hex": "010000fd",
      "revealed_at_utc": "2026-05-29T22:41:52.860943+00:00"
    }
  ],
  "meta": {
    "generated_at_utc": "2026-05-29T22:21:35.641583+00:00",
    "code_commit": "bad65e851449d0afa71dcded937661dc128b21a9"
  },
  "extractor": {
    "seed_source": "https://drand.cloudflare.com/public/latest",
    "seed_value": "714da9c52772f4b314e5bbf6e6999b537dff8f47b9c1b25dff99ddd7e8a8895a",
    "window": 256,
    "output_bits": 256,
    "output_hex": "6da672b0afd541b78e81b7b461e22d522e85c89a6cebefdc83dabee34736e47b",
    "generated_at_utc": "2026-05-29T22:42:25.347032+00:00"
  }
}